c4sfcensusgeocoder/__init__.py
c4sfcensusgeocoder/batch_geocoder.py
c4sfcensusgeocoder/cli.py
c4sfcensusgeocoder-0.0.12.dist-info/LICENSE
c4sfcensusgeocoder-0.0.12.dist-info/METADATA
c4sfcensusgeocoder-0.0.12.dist-info/WHEEL
c4sfcensusgeocoder-0.0.12.dist-info/entry_points.txt
c4sfcensusgeocoder-0.0.12.dist-info/top_level.txt
c4sfcensusgeocoder-0.0.12.dist-info/RECORD
