Metadata-Version: 2.1
Name: c4sfcensusgeocoder
Version: 0.0.12
Summary: Censusgeocoder
Home-page: https://github.com/sfbrigade/c4sf-censusgeocoder
Author: Data Science Working Group - Code for San Francisco
Author-email: datascience@codeforsanfrancisco.org
License: UNKNOWN
Platform: UNKNOWN
Classifier: Programming Language :: Python :: 3
Classifier: License :: OSI Approved :: MIT License
Classifier: Operating System :: OS Independent
Requires-Dist: censusgeocode
Requires-Dist: pandas
Requires-Dist: click
